vietokenizer/__init__.py
vietokenizer/constant.py
vietokenizer/preprocess_load.py
vietokenizer/tokenizer.py
vietokenizer-1.0.3.dist-info/LICENSE
vietokenizer-1.0.3.dist-info/METADATA
vietokenizer-1.0.3.dist-info/WHEEL
vietokenizer-1.0.3.dist-info/top_level.txt
vietokenizer-1.0.3.dist-info/RECORD
