Metadata-Version: 2.1
Name: vietokenizer
Version: 1.0.3
Summary: Vietnamese Tokenizer package based on deep learning method
Home-page: https://github.com/Nguyendat-bit/VieTokenizer
Author: Dat Tien Nguyen
Author-email: nduc0231@gmail.com
Maintainer: Dat Tien Nguyen
Maintainer-email: nduc0231@gmail.com
Keywords: vietokenizer
Classifier: Development Status :: 3 - Alpha
Classifier: Intended Audience :: Developers
Classifier: Programming Language :: Python :: 3.7
Classifier: License :: OSI Approved :: Apache Software License
Classifier: Operating System :: OS Independent
Requires-Python: >=3.7
License-File: LICENSE
Requires-Dist: tensorflow (>=2.8.2)
Requires-Dist: gdown (>=4.4.0)
